{
  "_class": "symbolInstance",
  "booleanOperation": -1,
  "clippingMaskMode": 0,
  "do_objectID": "9F22C757-4C59-4520-827B-5EA8909F1D81",
  "exportOptions": {
    "_class": "exportOptions",
    "exportFormats": [
    ],
    "includedLayerIds": [
    ],
    "layerOptions": 0,
    "shouldTrim": false
  },
  "frame": {
    "_class": "rect",
    "constrainProportions": false,
    "height": 54,
    "width": 351,
    "x": 5,
    "y": 0
  },
  "hasClippingMask": false,
  "horizontalSpacing": 0,
  "isFixedToViewport": false,
  "isFlippedHorizontal": false,
  "isFlippedVertical": false,
  "isLocked": false,
  "isVisible": true,
  "layerListExpandedType": 1,
  "name": "Nasi Campur",
  "nameIsFixed": true,
  "overrideValues": [
    {
      "_class": "overrideValue",
      "overrideName": "9CC7A50D-23AC-466A-81C5-000DB1579DEC/36A6D051-5D1D-4BDB-99F1-C3E9DD56B9F1/5EC66DFB-57B4-4C51-95CD-D71707B53102_stringValue",
      "value": "Nasi Campur"
    },
    {
      "_class": "overrideValue",
      "overrideName": "9CC7A50D-23AC-466A-81C5-000DB1579DEC/36A6D051-5D1D-4BDB-99F1-C3E9DD56B9F1/D0A983C1-BF8E-4647-9C84-6EA2A545BAF8_stringValue",
      "value": "Salty, Spicy, Umami"
    },
    {
      "_class": "overrideValue",
      "overrideName": "4A7D3847-FB48-4C66-B5A3-CE0187947ACD_image",
      "value": {
        "_class": "MSJSONFileReference",
        "_ref": "images/1cef523507e060c5cb85d0be0faf7709ce6e8cf3.png",
        "_ref_class": "MSImageData"
      }
    }
  ],
  "resizingConstraint": 63,
  "resizingType": 0,
  "rotation": 0,
  "scale": 1,
  "shouldBreakMaskChain": false,
  "style": {
    "_class": "style",
    "blur": {
      "_class": "blur",
      "center": "{0.5, 0.5}",
      "isEnabled": false,
      "motionAngle": 0,
      "radius": 10,
      "saturation": 1,
      "type": 0
    },
    "borderOptions": {
      "_class": "borderOptions",
      "dashPattern": [
      ],
      "isEnabled": true,
      "lineCapStyle": 0,
      "lineJoinStyle": 0
    },
    "borders": [
    ],
    "colorControls": {
      "_class": "colorControls",
      "brightness": 0,
      "contrast": 1,
      "hue": 0,
      "isEnabled": false,
      "saturation": 1
    },
    "contextSettings": {
      "_class": "graphicsContextSettings",
      "blendMode": 0,
      "opacity": 1
    },
    "do_objectID": "317A2DD8-3096-4A3A-9147-6A1C4E96771C",
    "endMarkerType": 0,
    "fills": [
    ],
    "innerShadows": [
    ],
    "miterLimit": 10,
    "shadows": [
    ],
    "startMarkerType": 0,
    "windingRule": 1
  },
  "symbolID": "808D7F23-E851-4DF6-9747-62A25B899797",
  "verticalSpacing": 0
}